launchdarkly_drf/__init__.py
launchdarkly_drf/apps.py
launchdarkly_drf/provider.py
launchdarkly_drf/views.py
launchdarkly_drf-0.1.0.dist-info/WHEEL
launchdarkly_drf-0.1.0.dist-info/METADATA
launchdarkly_drf-0.1.0.dist-info/RECORD
