Metadata-Version: 2.4
Name: launchdarkly-drf
Version: 0.1.0
Summary: A Django + DRF integration for LaunchDarkly feature flags
Keywords: django,launchdarkly,feature-flags,feature-toggles,flags
Author: Fullchee Zhang
Author-email: Fullchee Zhang <fullchee@gmail.com>
License-Expression: MIT
Classifier: Framework :: Django :: 4
Classifier: Framework :: Django :: 5
Classifier: Intended Audience :: Developers
Classifier: Operating System :: OS Independent
Classifier: Programming Language :: Python :: 3.12
Classifier: Programming Language :: Python :: 3.13
Classifier: Programming Language :: Python :: 3.14
Requires-Dist: django>=4.2
Requires-Dist: djangorestframework>=3.15
Requires-Dist: launchdarkly-server-sdk>=9.0.0
Requires-Python: >=3.12
Project-URL: Homepage, https://github.com/Fullchee/launchdarkly-drf
Project-URL: Issues, https://github.com/Fullchee/launchdarkly-drf/issues
Project-URL: Repository, https://github.com/Fullchee/launchdarkly-drf
